rpg_icon_generator/__init__.py
rpg_icon_generator/generator/__drawing.py
rpg_icon_generator/generator/__generator.py
rpg_icon_generator/generator/__init__.py
rpg_icon_generator/generator/__pattern_generator.py
rpg_icon_generator/generator/armor.py
rpg_icon_generator/generator/axe.py
rpg_icon_generator/generator/blade.py
rpg_icon_generator/generator/hammer.py
rpg_icon_generator/generator/potion.py
rpg_icon_generator/utils/__init__.py
rpg_icon_generator/utils/bound.py
rpg_icon_generator/utils/color.py
rpg_icon_generator/utils/constants.py
rpg_icon_generator/utils/misc.py
rpg_icon_generator/utils/random.py
rpg_icon_generator/utils/vector.py
test/__init__.py
test/test_armor_generator.py
test/test_axe_generator.py
test/test_blade_generator.py
test/test_docs_images_generator.py
test/test_hammer_generator.py
test/test_pattern_generator.py
test/test_potion_generator.py
rpg_icon_generator-0.5.0.dist-info/LICENSE
rpg_icon_generator-0.5.0.dist-info/METADATA
rpg_icon_generator-0.5.0.dist-info/WHEEL
rpg_icon_generator-0.5.0.dist-info/top_level.txt
rpg_icon_generator-0.5.0.dist-info/RECORD
