Metadata-Version: 2.1
Name: rpg-icon-generator
Version: 0.5.0
Summary: This package generate RPG items images procedurallye
Home-page: https://github.com/Kl0ven/rpg-icon-generator
Author: Jean-loup Monnier
Author-email: jloup.m@gmail.com
License: UNKNOWN
Platform: UNKNOWN
Classifier: Programming Language :: Python :: 3
Classifier: License :: OSI Approved :: MIT License
Classifier: Operating System :: OS Independent
Requires-Python: >=3.6
Requires-Dist: drawSvg (==1.7.0)
Requires-Dist: Shapely (==1.7.1)
Requires-Dist: bezier (==2020.5.19)
